{"[deleted]": {}, "beldroy": {}, "Loui1999": {}, "FixGMaul": {}, "OroJ": {}, "angelakrewenchuk": {}, "Ada088": {}, "foodiezilla": {}, "fisk4rn": {}, "Rain_xs": {}, "MetalMan20XX": {}, "affzau5e": {}, "gpgpg": {}, "Mved": {}, "HolySpawn1": {}, "megha087": {}, "fribbe": {}, "addi087": {}, "dannzio": {}, "Cheesydude": {}, "rubysr": {}, "cloudrapking": {}, "Tj0cKiS": {}, "dolly087": {}, "Mewzen": {}, "ApocRising": {}, "j0ntex7": {}, "slimelia": {}, "studentday89": {}, "-BrinK": {}, "marianasuplicy": {}, "smithchristeenf77": {}, "mfvicli": {}, "Jalepino_Joe": {}, "AlbiteTwins": {}, "criticali": {}, "zkanabdullah2014": {}, "ShhDontTalk": {}, "KRAy_Z_n1nja": {}, "OkayAl": {}, "nin-jas": {}, "shoplamaniaus": {}, "PrincessTyphoon": {}, "Spaceyace": {}, "starofscape": {}, "makeoverbody": {}, "DebraTurner": {}, "magazinecafes": {}, "Avoutrie": {}, "Sa-horse": {}, "Shoppingover": {}, "Dulce22": {}, "Trapscape": {}, "F1ux07": {}, "simrankour350": {}, "Bovineguru": {}, "justj0rdan": {}, "libutterfly": {}, "YggdraYurilArtwaltz": {}, "unknown_aime": {}, "lordumoh": {}, "Vindictive_Hyena": {}, "B0PPED": {}, "InnocentBF": {}, "Latteus": {}, "Zaffety": {}, "lonliestwanderer": {}, "OSRS_NoVa": {}, "Brewi": {}, "RSCupOfTea": {}, "manvsture": {}, "sd5seandewar": {}, "PresidentProphet": {}, "And_Justice": {}, "samantwon": {}, "CrazyPankti11": {}, "alcomandatv": {}, "elonkok": {}, "EdHicks": {}, "Arohii": {}, "Plane-arium": {}, "Ikreb-Reddit": {}, "osrs2111": {}, "cjosbo": {}, "kitekat1": {}, "TranceScape": {}, "FLFFYdota": {}, "ALotOfNinjas": {}, "Fashionscape_Jess": {}, "Cyn0sure_": {}, "Imbadatstuffz": {}, "AJPENOSTALGIA": {}, "ChiefStriffy": {}, "JoshPlaysRS": {}, "HeyKidsDoUWantCandy": {}, "Robstrap": {}, "andrishh": {}, "hassanmaheer": {}, "melvynlennard": {}, "Toadbane": {}, "Hector247s": {}, "myrabev": {}, "wristbandbuddy": {}, "wearepvt": {}, "DAGIMAGES": {}, "FashionOnlineStore": {}, "kapitonas": {}, "storybooknerd": {}, "Kaorixx": {}, "Neesh_India": {}, "xuan135": {}, "ThatGuyThisTime": {}, "bridesmaiddesigner": {}, "fashiongossip": {}, "Viberin": {}, "Mists_": {}, "mykewlpro": {}, "Abel191": {}, "llghtly": {}, "bumdee": {}, "fashion112": {}, "michaljohnson36": {}, "ruspe": {}, "abhiashu530": {}, "Falcun55": {}, "douproductions": {}, "shadesandyoufashion": {}, "BonheurJewelry": {}, "gilbertrocs1": {}, "meibor": {}, "Departments": {}, "xXxFasHioNScaPeExXx": {}, "MaralYazarloo": {}, "mfl91": {}, "youngmetroyoungmetro": {}, "thesmallpercentageof": {}, "Annajones12": {}, "Kasumi_Eric": {}, "saundrea12": {}, "deposit17": {}, "NoxLD": {}, "ragemrat": {}, "hairstyleslife": {}, "tanishka_basu": {}, "Inblogslife": {}, "Saratonein": {}, "ngoquyen938": {}, "DestinyIsDestiny": {}, "LingerieCorner": {}, "Sohini1": {}, "iWantALongNameToo": {}, "ajayseo123456": {}, "Lamodeluxe": {}, "renegadeusername": {}, "vasundharakutumbham": {}, "alanic60": {}, "vinshon": {}, "RetaEhtMaerd": {}, "stofoo": {}, "TugaScaper": {}, "Alina2Gomes": {}, "William2noa": {}, "bridalfeelnz": {}, "ATileFloor": {}, "fashiondresss5": {}, "fashiondresss111": {}, "Dencyrichi": {}, "braddelson73": {}, "Haakkus": {}, "majestic_firby": {}, "jacob_ninja_potato3": {}, "Lordpleasur": {}, "NaJinDuke": {}, "DolanRS": {}, "Zerosiz": {}, "theonlyon3": {}, "Kryptical": {}, "Tasoa3": {}, "mxwurtz": {}, "uvurs": {}, "Jopez-": {}, "brunchU": {}, "ltsDarkOut": {}, "Nightman96": {}, "PervyCacti": {}, "ChadDouchebaggington": {}, "DavyKer": {}, "lloyd299": {}, "TheElderGregg": {}, "Harkian": {}, "LifeIsSmrt": {}, "Slimeyz": {}, "Hoanganh93": {}, "Bene449": {}, "Aeehnrst": {}, "chrlkw8": {}, "reset5": {}, "Googii": {}, "HurtOfIntention": {}, "nissehb": {}, "TrackpadEasy": {}, "Kcwidman": {}, "huhwynaut": {}, "fuckjayce": {}, "Boss1nGobl1n": {}, "Green272": {}, "Blackened-Wings": {}, "Laheyahey": {}, "_saccharine": {}, "Master_Yi_Brad": {}, "PuggySs": {}, "BearConstellation": {}, "Shut_Yo_Meowth": {}, "OSRS-ZW0ARK96": {}, "hellslasher": {}, "sleeptabo": {}, "HSThrow": {}, "Agility-Icon": {}, "Ladders1o1": {}, "El_Rosado": {}, "CptTeddy": {}, "wilkins348": {}, "DeadManMode": {}, "kmchii": {}, "agentjor": {}, "Banlaine": {}, "VoidVeno": {}, "negy": {}, "dimes2dope": {}, "yipyipsean": {}, "Kkeifer": {}, "Hotaru_Fox": {}, "Soupremechaos": {}, "DrugsProbably": {}, "Puddinglax": {}, "internetguy__": {}, "Tabj17": {}, "Sir_Richard_VII": {}, "PrudencePetiteStyle": {}, "ineedahashtag4myswag": {}, "MonsieurAuguste": {}, "lashkaraa2015": {}, "pouchme77": {}, "sophialindae": {}, "modxchangeus": {}, "toscee": {}, "Vestar5": {}, "aquaazulboutique": {}, "CThomas1265": {}, "seolenspick": {}, "ClyntonM": {}, "Xx_Pattie_xX": {}, "purpleslug": {}, "exbasi": {}, "trick_shop": {}, "sponlox": {}, "Phoenix---Fire": {}, "Lva_": {}, "Cuezaltzin": {}, "iTristan": {}, "Luvas": {}, "lisabelsesi": {}, "ICJUK": {}, "feelingfeels": {}, "1_underscore": {}, "catflower117": {}, "DCOFashion": {}, "vogue-fashion": {}, "MiddleEastBeast1": {}, "PrettyPoshFash": {}, "nyeaon": {}, "secretagentrandybean": {}, "DesignersAndYou": {}, "Jackstral": {}, "MrGreavok": {}, "robbingoods": {}, "_Doubt": {}, "iflauntme1": {}, "shivkumarbssi1": {}, "RspsLuffy": {}, "rubyxinn12": {}, "Siresadnoob": {}, "ManhCuongSai": {}, "AnzacsPride": {}, "jwood1289": {}, "MayaThomas19": {}, "vividartsy": {}, "iPlayAtW0rk": {}, "Giullaree": {}, "couldcarryless": {}, "BadPunsGuy": {}, "zaine757": {}, "LightBulb_Maniac": {}, "PM_ME_UR_OSBUDDYPRO": {}, "HayleyFair": {}, "Peanutcat4": {}, "killerjerick": {}, "trangkieuabc123": {}, "ResonantWill": {}, "LisaaRS": {}, "GlitteryJimmy": {}, "Legenditals": {}, "ch3m1cal": {}, "benzo_messiah": {}, "twohandedfap_": {}, "DaisyJeffery": {}, "R3lentless": {}, "surbhirathore": {}, "WarmupHero": {}, "Breiweaks": {}, "notoafkpray": {}, "jetzido": {}, "commonprincess": {}, "FreshAsFuq": {}, "thepenmen22": {}, "Cameronza": {}, "Juke07": {}, "Elite54321": {}, "modeincoton": {}, "RsGoldGuru": {}, "oliviagrey": {}, "digthisdesign": {}, "Bossdude234": {}, "MatticeV": {}, "sav_squatch": {}, "MoneyMike12": {}, "urban_direct": {}, "FeIiks": {}, "daffidel69": {}, "thomaspecellini": {}, "Abdur79": {}, "Shock-Jock": {}, "i8_2_l8": {}, "urdeadxd": {}, "Kleeqers": {}, "kreckon": {}, "pujaji": {}, "GStadnik": {}, "theteeplug": {}, "danigiesen1": {}, "MrEflox123": {}, "pattielowrance": {}, "HexaBags": {}, "Amberskittle": {}, "im_naughty": {}, "Gilrix": {}, "bradenwink": {}, "Chuklecow": {}, "tbenygma": {}, "Zulerah": {}, "BromarNL": {}, "worth_tendonitis": {}, "styl-inc": {}, "smashvw": {}, "BoobyBear": {}, "twistedsquare69": {}, "Dizzle07": {}, "loiloiloi6": {}, "TrinketSea": {}, "audreytaylor7389": {}, "clairesophie7389": {}, "lennard169": {}, "Lucky_Rs": {}, "Cadvahn": {}, "dministraitor": {}, "altguy3": {}, "me_grungesta": {}, "TacoBell1997": {}, "MFCaracara": {}, "xDEEFx": {}, "FamImWoke": {}, "fae2h": {}, "10IphonesIcarlyyyyyy": {}, "ElusiveDuckling": {}, "DailYxDosE": {}, "GreenBeanGuy": {}, "NukaCooler": {}, "Dizz1eRu1es": {}, "Fear_ltself": {}, "9Yo_Shrek": {}, "KyroRS": {}, "Causmedia": {}, "ActuallyWicker": {}, "TheAutomater": {}, "TonyS95": {}, "McFlyTheFuture": {}, "Keegonusmaximus": {}, "ayboo": {}, "Tomfavreau": {}, "donnie_the_dealer": {}, "Dryrr": {}, "JaidonP": {}, "kbrown5523": {}, "Chainsaw_slide": {}, "ajewe11": {}, "Jack_The_Mad": {}, "kokirisboots": {}, "Andsis": {}, "homuhomuu": {}, "jfdlaks": {}, "YUHDEW": {}, "EUROBRAH": {}, "Palikadude1": {}, "Ulltcombo": {}, "unholy_good": {}, "KBAREY": {}, "Quit_Asking": {}, "nbalivecoin": {}, "IamLetttuce": {}, "ArgyleGrant": {}, "roonyscoop": {}, "BabyBackBich": {}, "Chandlery": {}, "rjkucia": {}, "palibakufun": {}, "Parascyllium": {}, "Syphox": {}, "betweenOSRS": {}, "Rsnickclaus": {}, "Kayla_Crafty": {}, "CptHappyPants": {}, "unCiFy": {}, "Jammess95": {}, "Bennettjamin": {}, "HellsEnemy": {}, "Babalabaskreep": {}, "check_my_444": {}, "ILikeThisyes22": {}, "killaa": {}, "BigDaddyLaowai": {}, "Zer0Skilled": {}, "FirstNen": {}, "Gnome_Woman": {}, "Tokemonbattle": {}, "AyoRobin": {}, "Shmurdaah": {}, "DwarvenBard": {}, "RoryT32": {}, "lapride7": {}, "S_A_I_N": {}, "rama3600": {}, "LHBrady": {}, "Brandouken": {}, "xbrewtalityx": {}, "emmamegan1983": {}, "Studly_Spud": {}, "BlondeyFox": {}, "jerone7": {}, "Ellscape": {}, "Tiques": {}, "Augustane": {}, "luxurywaxbar": {}, "TheSaltyBiscuit": {}, "Hrsnn": {}, "Rainted": {}, "anastasia42o": {}, "Traynaa": {}, "dikkebmwhilda": {}, "Yo_Face_Nate": {}, "BarbarTowner": {}, "fashionwomania": {}, "demis3": {}, "FacemaskRS": {}, "SoulessMud": {}, "Bedcovers": {}, "shanice1fashion": {}, "fish94": {}, "-Momoe-": {}, "Cripzzaherino": {}, "ant191": {}, "AmaterasooRS": {}, "Icefirebet": {}, "BA_Horse": {}, "Scape4Lyfe": {}, "anup3131": {}, "MisterBuzz": {}, "Aierou": {}, "0hNooo_": {}, "fred1674": {}, "ConnorTheCatholic": {}, "Gods_Defence": {}, "GauTruc": {}, "Avionte99": {}, "nerve500": {}, "CEO2K16": {}, "live_lavish": {}, "fashiondresss4": {}, "Insereniity": {}, "5hu6ham5ahu": {}, "maycgee": {}, "SuffocatingBreed": {}, "unitys": {}, "emilyclayus": {}, "epicbryce1699": {}, "ArtGift": {}, "Ali_XCX": {}, "datagrid1416": {}, "dinomoriea": {}, "fashionscapeisbest": {}, "ItsLovell": {}, "maddoc74": {}, "gesitkonveksi": {}, "The_Dude_In_Torags": {}, "iplayrstoomuchnow": {}, "MeowingtonsCat": {}, "happycotton": {}, "Packyakinese": {}, "rajeshseo50": {}, "fassionme": {}, "Rabidsolution": {}, "Pine247": {}, "fate_wulluf": {}, "AskYouEverything": {}, "LeJunkie420": {}, "Thefixedbroken": {}, "CUNT_MASHER": {}, "hansdeo": {}, "Phlum": {}, "agle487068": {}, "camstoker": {}, "Natinals": {}, "Waitinhere": {}, "sfsdgsdgsdgsd": {}, "I3rightside": {}, "Rain_x": {}, "fknhansfgt": {}, "benkozak1": {}, "NebbTheGreat": {}, "Multitask07": {}, "shopgrayarch": {}, "Frag3d": {}, "zelmarose": {}, "polegars": {}, "lanternau": {}, "Galderma": {}, "BasedScape": {}, "F99C": {}, "Norrie21": {}, "TruthAlone": {}, "APXCrashendo": {}, "RocketPropelledHiFiv": {}, "Whitmad": {}, "Plsnomayne": {}, "onplaza": {}, "Jerryified": {}, "magazineelux": {}, "wissmanbarret": {}, "PterobleIan": {}, "-RinTohsaka-": {}, "dukebubs": {}, "arnoldstatham7": {}, "TorgOnAScooter": {}, "Comilion": {}, "ScumbagSupreme": {}, "dbkstylez": {}, "98rhv9uaenrhfi": {}, "infineks": {}, "ObTwo": {}, "azurbikinicom": {}, "kobe238": {}, "KebabHyvlaren": {}, "amiitty": {}, "oblooq": {}, "addisonwill87": {}, "Yusuffadzil": {}, "allthingstrendy": {}, "adrianpark01": {}, "sakhifashions": {}, "Zajimo": {}, "Nca1996": {}, "fairyborn": {}, "Delaemera": {}, "jbdcollection": {}, "Valac_SaiyajiN": {}, "rarescape": {}, "Shills_are_REAL": {}, "SonniD": {}, "NaughtonBraun": {}, "jwalke9": {}, "KoningKoen": {}, "odishasareestore": {}, "Dancingfuhrer": {}, "PoundofQualityCheese": {}, "Sir-Cumsize": {}, "witeboie": {}, "Demetre130": {}, "Harudoku": {}, "robbomate": {}, "Multimarkboy": {}, "prepareuranus69420": {}, "Botoz": {}, "renyzen": {}, "Dreamwire": {}, "leenasingbal": {}, "Wheatiez": {}, "Moth3r_1n_l4w": {}, "luismendes6": {}, "DerkRS": {}, "Zironio": {}, "TonyRockWalker": {}, "befunkies": {}, "curatedluxe": {}, "exclusivemillionaire": {}, "fashiongirlss": {}, "yamamaycollection": {}, "trendypatterns": {}, "SerickM8": {}, "DaFronts": {}, "MattIfNeedBe": {}, "dresses1211": {}, "Poowdoh": {}, "Eeehhhhhh": {}, "millsgrace7": {}, "efrea": {}, "Blexie": {}, "KuribohFTW": {}, "FroggleG": {}, "SuchUserMuchName": {}, "barabarasalimop": {}, "Alo360": {}, "countd0wn": {}, "hamymy": {}, "Cha_rlesRS": {}, "OhManTFE": {}, "lordoftheaxes": {}, "DoubleTreePgh": {}, "JinMah": {}, "nightwing412": {}, "TuckVA": {}, "AzureLight7": {}, "GENERAL_GENTLEMAN": {}, "GiantCaveSpider": {}, "aPentagram": {}, "Xyanide01": {}, "ghazala786": {}, "nskorphan": {}, "snuffl3upagus": {}, "Fragginzz": {}, "anon5481": {}, "lovejordankicks": {}, "Klayshark": {}, "Danny_217": {}, "jdawgg0": {}, "livinglitch": {}, "mariafarnendes": {}, "james593": {}, "le_crux": {}, "gloriajmalone100": {}, "GreatestAuk": {}, "YourzNotMine": {}, "OfficialTaurus": {}, "-Kaan-": {}, "AlishaKapoor11": {}, "bernbeck": {}, "golivexplore": {}, "masseffectwomen": {}, "theslackerstyle": {}, "orgotime": {}, "sonalbisht101": {}, "colBAE": {}, "RitaDias316": {}, "TurnipG": {}, "Im__so_sorry_guys": {}, "leDesespoir": {}, "Bane_of_Minorities": {}, "Alcyonia": {}, "Inner_Mathematician": {}, "Silhzze": {}, "s3iman": {}, "InkFoxclaw": {}, "young_mula": {}, "EzraCG1991": {}, "xEREBOSx": {}, "j0m0k": {}, "Coolnuggets": {}, "osrs_fashionscape": {}, "skeptz": {}, "Jonisabon": {}, "Murphstarr": {}, "VardenRS": {}, "MilkmanGaming": {}, "porkayy": {}, "Almond_the_Nut": {}, "akordaan": {}, "saturnsnow": {}, "Diluvie": {}, "SacKingsRS": {}, "Phoxey": {}, "VapeOnRanarr": {}, "Fridgiee": {}, "NossyOnThe": {}, "dicrypt": {}, "Naknakha": {}, "_LuckyBlue_": {}, "LanthusV": {}, "HossTM": {}, "virginpolice69": {}, "JovianJewels": {}, "Aphoniah": {}, "lcPASCAL-": {}, "DownToTuturuu": {}, "trojanmann22": {}, "TripTankApe": {}, "N7Drow": {}, "ChinookNL": {}, "santabootswhy": {}, "vainlikeme": {}, "elblife": {}, "Ugandulu": {}, "LookStyler": {}, "SirDobo": {}, "BespokeBeauty": {}, "me_irl_wont_upvote": {}, "aresman71": {}, "AlmightyCo": {}, "iebebravetextiles": {}, "joshallen0321": {}, "adamjoneso": {}, "kmozifashion": {}, "IleenJasmine17": {}, "LeonaPaul": {}, "Baenisme": {}, "Minginmetch": {}, "Saddams_Zucchini": {}, "NuovaShowroom": {}, "420Swagrid420": {}, "COINTELPROxShareBlue": {}, "frankoket": {}, "TakeBlows": {}, "VulcanMag872": {}, "Jleduff": {}, "Deanironman": {}, "Nogts": {}, "cxwxo": {}, "cookieinsanity": {}, "MuhGeexoxo": {}, "Rominix": {}, "Kazuma126": {}, "georgisaur97": {}, "ikillsi": {}, "jake_kulp": {}, "Tynadoes": {}, "hermistoner99": {}, "Goodwin512": {}, "Marjakossu": {}, "VictorXGaming": {}, "FriedChopstyx": {}, "Paddo127": {}, "Tookarn": {}, "Forex_trader99": {}, "moomentsgiftcards": {}, "dressrighau": {}, "Captainplop": {}, "LingerieBriefs": {}, "uptown18dotcom": {}, "theonewhosmells": {}, "Norune": {}, "balancy": {}, "conceferoz": {}, "Devairen": {}, "200201552": {}, "stackinyews": {}, "GraysonSmels": {}, "Stackly": {}, "Zainiizubair": {}, "TheDoctorOnRs": {}, "DestyX": {}, "The_Jeremy": {}, "Ificouldslaynoise": {}, "SolidEnvy": {}, "Sicai": {}, "waveringkaos": {}, "drop_an_imp": {}, "RSbooll5RS": {}, "grexus": {}, "Heisenberg_RS": {}, "Chaosten": {}, "PhenomenonYT": {}, "One_For_Twenty": {}, "BossBoltage": {}, "Jabroniiii": {}, "Duckyyyyyy": {}, "Rashiddd": {}, "Mercury_Reos": {}, "El_Jesse": {}, "mcfaiils": {}, "SharkBrew": {}, "Lorenz__": {}, "RealityReid": {}, "BootyHorse": {}, "MrMole73": {}, "Gigantoops": {}, "choderodeo": {}, "xMoneyB": {}, "TheSpencerCain": {}, "Madsbp22": {}, "TheRimReaperz": {}, "lil_pun": {}, "AWStigs": {}, "Imanobv2": {}, "Hvmildvs": {}, "0600AM": {}, "Southpark045": {}, "TakeMyDamnUsername": {}, "MChez": {}, "ZumZumBumBum": {}, "Joelg4": {}, "legoknight": {}, "veetim": {}, "maryjanewatson65": {}, "Questpurex10": {}, "thelordofhell34": {}, "mnelliot": {}, "conbreadboi": {}, "MrPenguino29": {}, "Sharpie669": {}, "WolfzOSRS": {}, "JoJoPanda": {}, "meowscape": {}, "PlayerDeadstar": {}, "DarthNekros": {}, "Dixon_harass": {}, "Im_Mola": {}, "NotMyOreos": {}, "BenjaminPls": {}, "Zymophilus": {}, "CuteDevilDrawings": {}, "Nexer_": {}, "EyeZombot": {}, "corradaspatola": {}, "B52-Psycho": {}, "fawkwitdis": {}, "JakePelican": {}, "Everlasting_Mystery": {}, "ShinyBidoof7654": {}, "A_Random_Teenager": {}, "mooimabird": {}, "Parlanceee": {}, "Brofare": {}, "_Hydro": {}, "WhatsThisMess": {}, "Fauxfade": {}, "ArpyClarkson": {}, "zt4t1c": {}, "browningtons": {}, "_dontkillme": {}, "danrick": {}, "hawks_gold": {}, "-Viktoria": {}, "DefaultMangar": {}, "Gsuuuus": {}, "lngoo": {}, "gekosaurus": {}, "Biotiqueayurvada": {}, "Jehovanoid": {}, "matthiux": {}, "Wekmor": {}, "it_me_waifu": {}, "MyUsernameCantFi": {}, "420harry": {}, "krossbarkev": {}, "ScytheSergeant": {}, "Guynecologist": {}, "SockeyeSnow": {}, "DreamMentor": {}, "rsyay": {}, "_zg_": {}, "wakenmasturbate": {}, "snobb": {}, "Tainted_OneX": {}, "Player_B": {}, "aflackguy": {}, "zajer": {}, "1993teemu": {}, "Luckybuckets": {}, "JonBargan": {}, "Owl9": {}, "boreltje": {}, "b0en": {}, "TrashLurker": {}, "Pinguuuuuuuu": {}, "yBrony": {}, "mai_L": {}, "Parthuurnax": {}, "iron_enix": {}, "WhyPilz": {}, "iQz": {}, "RainbowDudee": {}, "Girlgamer42": {}, "IdsRS": {}, "Athemoe": {}, "Mr_Smithers1": {}, "TDoe21": {}, "Clayblud": {}, "TheHoblit": {}, "sppbsu": {}, "zhwedyyt": {}, "ProtoBeta": {}, "LysergicAcidDiethyla": {}, "Tunnelunder": {}, "flarm2": {}, "fultonsoccer7": {}, "Trust_Me_Im_A_Duck": {}, "ravsuv": {}, "Snowfoo": {}, "Ethnics_Wash_My_Car": {}, "dingdong420blaze": {}, "Aerodamus": {}, "Bigpoppa79": {}, "le--er": {}, "bilobob": {}, "The_Fastest_of_Foods": {}, "Skyrider70": {}, "Rahshindra": {}, "CactiChill": {}, "utfanx2": {}, "Lord_Marrowgar": {}, "iskillsy": {}, "MinnesotaUnited": {}, "trowels": {}, "doyagib": {}, "glowbaby": {}, "andrew0896": {}, "EEyland": {}, "AasianApina": {}, "LittleT0m": {}, "Pjup": {}, "zn95": {}, "KushosaurusRex": {}, "Is_OP": {}, "Marcooon": {}, "FisherRS": {}, "cyndarella": {}, "L3ft": {}, "FPS_sam": {}, "adcmainorfeed": {}, "Rundown93": {}, "AlcatrazRs": {}, "HeistOnRS": {}, "My_Fox_Hat": {}, "liamde123": {}, "PomegranateExplosion": {}, "Hi_mister": {}, "RSRokyen": {}, "LiterallyABlunt": {}, "kolane99": {}, "TerminallyNostalgic": {}, "Teecu": {}, "LiveFree1773": {}, "thisisunreal": {}, "R1ckster": {}, "Jethric": {}, "Own7g3RS": {}, "Zelotic": {}, "FancyThief": {}, "Jaolinlol": {}, "food_is_crack": {}, "toad_family": {}, "HitOrSit": {}, "createdfordota2": {}, "Fear_The_Neard": {}, "CptAverage": {}, "Arkeaus": {}, "Is_This_Invalid": {}, "Reheat_": {}, "98Skiller": {}, "Lambeaux": {}, "rambi2222": {}, "new2baseball": {}, "HalfPastTen": {}, "RetardFridge": {}, "Murmillion": {}, "GodsAreTired": {}, "Elonysis": {}, "MisterPandah": {}, "sirderkmang": {}, "cilohapirt": {}, "skinhawk": {}, "xWooney": {}, "sacrel": {}, "Jokershores": {}, "Bo_Dallas": {}, "Hayden370": {}, "taybear12": {}, "ZZilovebeavers": {}, "ehShaun": {}, "9ty2": {}, "Raltz-z": {}, "Yagami_Light_07": {}, "SteveSnitzelson": {}, "abek809": {}, "GingerCnut": {}, "wiener78": {}, "j3al0uz": {}, "thefinalep": {}, "Goaterbiker": {}, "Blocksbro": {}, "Swavour": {}, "Swing_Doom1": {}, "I_was_Simon": {}, "Kingknlghtt": {}, "benittybop": {}, "DirectImageLinkerBot": {}, "Illustria": {}, "LandOwningPoet": {}, "LawnGnomeOSRS": {}, "Yingir": {}, "Hawk-Gate": {}, "rotorain": {}, "Jafooolay": {}, "Sinternet": {}, "Magnetic_Knives": {}, "BlogSpammr": {}, "Slyestcat": {}, "rollingdubsget": {}, "Joux540": {}, "Someone9339": {}, "AgathaKnights": {}, "Parzius": {}, "permanent_stalker": {}, "Lordington": {}, "jtrondy": {}, "flash19950": {}, "AxS-PixelBass": {}, "Hydroshi": {}, "dxlxn": {}, "undergrin": {}, "BaconCheesePie": {}, "ajlennox": {}, "Zippow": {}, "haleyhu": {}, "DoctorZoidberg_PhD": {}, "MUFCBoothy": {}, "Tooooooasty": {}, "S1R": {}, "Sakonipeurus": {}, "TheCatnamedMittens": {}, "blumpkin_beast_666": {}, "Hairy_Balsagna": {}, "wrkz": {}, "ocarinzee": {}, "NOT_A_BORGIA": {}, "kagelar": {}, "jooodles": {}, "420xxBLZitFGTxx69xx": {}, "Jusevan": {}, "RuneBoot": {}, "Shadurr": {}, "SkitZa": {}, "HelloThere62": {}, "TTTeltdown": {}, "Juizy": {}, "TheGotherax": {}, "tasseIs": {}, "jeroendj3": {}, "osrslol": {}, "mayugod": {}, "PregnantMale": {}, "Supreme-Goblin": {}, "von_leon1": {}, "Olympus_Robust": {}, "Leeeroyyy": {}, "Aionlight": {}, "TiggehCH": {}, "OMGitsSamRS": {}, "Gagged-": {}, "OSRS_Geo": {}, "tortoisetrot": {}, "originaldd": {}, "HallowApollo": {}, "therealgodfarter": {}, "Fubatsu": {}, "MyNameIsKiko": {}, "fatlazar123": {}, "draanexle": {}, "NauseousLava": {}, "An1m4ti0n": {}, "Cvelbar": {}, "Hasmond": {}, "World_333": {}, "Sl1ngdad": {}, "PkmnCloner": {}, "vibeless_": {}, "scagy": {}, "Cageweek": {}, "-Cloudy": {}, "Im_Beats": {}, "Snortallthethings": {}, "KappaJappa": {}, "third_member": {}, "unshiny": {}, "Guurk": {}, "ipwnedx": {}, "ManjaManja": {}, "Titavek": {}, "Mugsh0tz": {}, "TripperBets": {}, "bunnae": {}, "LastTroll": {}, "cciivvii": {}, "Carlhenrik1337": {}, "Doubtstand": {}, "SGTSHOOTnMISS": {}, "kxro": {}, "AleksandrVolkov": {}, "Patticuslore": {}, "Supergigala": {}, "Kumagor0": {}, "feargal98": {}, "ImNrV": {}, "Giddy_Up_Rs": {}, "eelekeah": {}, "GameChaos": {}, "Chobotinurmom": {}, "Muthix": {}, "iSoloMoms": {}, "Bestrin": {}, "jxyzits": {}, "imnublet": {}, "alchmagiclongs": {}, "clefairykush": {}, "Tularean": {}, "LouisJenkin": {}, "ZeoxeoRS": {}, "IBRACTIVE": {}, "GumDropWarrior": {}, "DylanModz": {}, "notabotjustamacro": {}, "blackfire108": {}, "torcfc": {}, "antflga": {}, "Mellow-as-fuk": {}, "Dc_Infinity": {}, "IwannaKnow8274": {}, "Lillestoel": {}, "akasdt": {}, "Ephixaftw": {}, "Oxgmum": {}, "ILearnToPhotoshop": {}, "Jebwan": {}, "ZePotato": {}, "SenpaiSkeleton": {}, "Urfarah": {}, "brb_taking_a_poo": {}, "Tannernator": {}, "flower_bot": {}, "Kryticul": {}, "deadrab6its": {}, "VapeScaper": {}, "McShuckle": {}, "TM32YourMom": {}, "I_Blame_Tom_Cruise": {}, "BenCannibal": {}, "Snacks456": {}, "imgiolol": {}, "Chainskirt": {}, "J_Bowks": {}, "imtiredtoo": {}, "QpangRL": {}, "yourewelcome_bot": {}, "DesignatedDiverr": {}, "mattstanton": {}, "yollamt": {}, "Eyezin": {}, "Roflcawptur": {}, "kuhataparunks": {}, "WhiteHawk93": {}, "nurmzyy": {}, "Aphelien": {}, "Omnitaco": {}, "Irignation": {}, "tetri5": {}, "GoobyExe": {}, "bentowny96": {}, "rrandyy": {}, "zomatroll": {}, "ig2s4tg": {}, "KClarkeh": {}, "AtheosLoL": {}, "Pashweetie": {}, "healslutthrowaway1": {}, "fuckCARalarms": {}, "Wooltar1": {}, "Gondyval": {}, "Mrsilhouettes": {}, "DieLichtung": {}, "Eawdude": {}, "a_FREAK_like_me": {}, "foxape": {}, "DankMemesWetDreams": {}, "dsbatt01": {}, "qoznyyy": {}, "vadhander": {}, "SimpleFlips": {}, "BelgianPvP": {}, "rubthatduck": {}, "PartyHatDude": {}, "asdfghjkl-_rs": {}, "MethLeppard": {}, "Wiggyboy24": {}, "Eternalnami": {}, "FPettersson": {}, "Mr_Muscle5": {}, "PM_PASSABLE_TRAPS": {}, "Jwrichard": {}, "xxplanexx1": {}, "suck_fpez": {}, "Iron_Disciple": {}, "zachowie": {}, "SenorGiggles": {}, "Huxta": {}, "Satan_Himselff": {}, "2Spooky4Head": {}, "Spideraphobia": {}, "Eiox": {}, "MuricanSniper": {}, "holyzagix": {}, "ologiic": {}, "BinaryFlame": {}, "Liwetha": {}, "Osrscrocodilers": {}, "Livi_faial": {}, "aarontbarratt": {}, "RSNKINGJOSH": {}, "zerquest": {}, "fluesday": {}, "Khlasified": {}, "wormyboi": {}, "EuphoricElf": {}, "DIY_Nihilism": {}, "GucciMonk": {}, "oscarw22": {}, "mrflowrence": {}, "Cookandcaughtup": {}, "yoimjoe": {}, "ZyzzTM": {}, "sexualmole": {}, "silverligth3": {}, "star-dog": {}, "hvydendrew": {}, "osrsqueen": {}, "matrix_ducati": {}, "gowey": {}, "Disheartend": {}, "OSRStask": {}, "Versitox": {}, "Seitzyyt": {}, "Cocksack399": {}, "Alexvincentt": {}, "Varicious": {}, "st4rgasm": {}, "PicDescriptionBot": {}, "RunEnabled": {}, "mc_zimo": {}, "surelythistime": {}, "Flawnks": {}, "Robb598": {}, "Rayne02": {}, "PraiseAbortion": {}, "kaasbaasoprs": {}, "badLuckm9": {}, "dootimes3": {}, "GG77R6": {}, "Coke4Cats": {}, "Dapaganator": {}, "RAMMERBAMER24": {}, "imguralbumbot": {}, "Jishnu_S": {}, "Gyazo_Bot": {}, "d0wl": {}, "TheCheesy": {}, "abyssalwhipped": {}, "GoldenBacon": {}, "Xen_Yuropoor": {}, "TheCrimsinChin16708": {}, "Z6ss": {}, "mayhempk1": {}, "VitruviusII": {}, "Krissu1337": {}, "teiohix": {}, "A95J": {}, "CarterBennett": {}, "loop_and_swoop": {}, "engiqueerical": {}, "Iophia": {}, "Muslim_Pilot": {}, "iResmas": {}, "ReheatFrozenChicken": {}, "PitbyHD": {}, "ScamPink": {}, "CVNDY": {}, "Syn666A7x": {}, "-Watts": {}, "Foxtrot_4": {}, "KVirello": {}, "EiB_LT": {}, "Bilsendorfdragmire": {}, "BertimusP": {}, "Tomsonas": {}, "SirJosias": {}, "-Wargrave-": {}, "Shockzyy": {}, "Samakka": {}, "OMPrismo": {}, "Dupemeister": {}, "CorvestA": {}, "Rocktica": {}, "retro_rocket": {}, "spaclock": {}, "Apoctopia": {}, "TreasuredSoul": {}, "Numericality": {}, "reb1995": {}, "afluffytail": {}, "HNCGod": {}, "Jokuhemmi": {}, "MyMegami": {}, "Henpai": {}, "skellyton3": {}, "Barry_Blue": {}, "rsalj": {}, "marmaladeftw": {}, "Random-Idea": {}, "RuneWave": {}, "slaytuna": {}, "TheRealSoloSickness": {}, "gifv-bot": {}, "MisterEsports": {}, "TheStormWonder": {}, "CLOUDY_SLEEP": {}, "MeteorKing": {}, "Flashyshooter": {}, "RCMakoa": {}, "iceler1": {}, "G3TR1CH": {}, "acww": {}, "BarelyLegalZ": {}, "Daejarvoe": {}, "Maraudi": {}, "_dialup": {}, "zhoudynsty": {}, "battl3rme": {}, "TheFarticleParticle": {}, "RIKHAL": {}, "Wood_Jew_Could_Jew": {}, "EIfinlocks": {}, "Tipsy_Pilot": {}, "Mr_Second_Amendment": {}, "Agrees_withyou": {}, "GoodBot_BadBot": {}, "xCookieHF": {}, "Hittintheroad": {}, "Oilight": {}, "JakePhillips52": {}, "Africk99": {}, "xiMAX1MUSix": {}, "zeptaaa": {}, "Jentsuu": {}, "muthafukinjohnny": {}, "GlaveEndou": {}, "Holshh": {}, "Hy_ce": {}, "Fuzzy_Ball44": {}, "soccer130": {}, "rawdawg88": {}, "Zentillion": {}, "YellowSucks": {}, "SexxyWaffles": {}, "Sailor_Venusaur": {}, "PyrrhaFan": {}, "wqzu": {}, "treedot": {}, "laidbackcomedian": {}, "jmfinfrock": {}, "NobIank": {}, "Darnit_Bot": {}, "Benskien": {}, "ocean_alley": {}, "SmackSmackk": {}, "Creative_Wizkid": {}, "Sexy_Wales": {}, "GMGarrison94": {}, "YourLocalPotDealer": {}, "nanjero": {}, "flinjager123": {}, "0urlasthope": {}, "jacksonpm23": {}, "ShenlingCaramel": {}, "brainsnaprecs": {}, "Odysseus_is_Ulysses": {}, "smellynelly123": {}, "Oohwshitwaddup": {}, "tictac4609": {}, "elemant56": {}, "FondledbyLions": {}, "412thetwins": {}, "timezone_bot": {}, "mmotush21": {}, "newuser2491": {}, "ShrinkRays": {}, "UnnecesaryAdjunctary": {}, "Arc_ChrisRS": {}, "PeppaPigDrinkingGame": {}, "Loukey95": {}, "Flesh_Carnival": {}, "freddyolo": {}, "RealWeaponAFK": {}, "Parfaii": {}, "cloktowahh": {}, "zlozmaj": {}, "Deagin": {}, "Buddha-Christ": {}, "Faelar": {}, "alowkeyloki": {}, "Nayeba": {}, "weezgang": {}, "Captain_Piratedanger": {}, "blushbitten": {}, "Mitt_Romnipples": {}, "drusepth": {}, "Pawneee": {}, "sillyguy69420": {}, "Sonju11": {}, "goodnamewanted": {}, "Risk_of_Pain": {}, "ki299": {}, "keeper_of_the_groove": {}, "phonebatterylevelbot": {}, "soepbord": {}, "Algotify": {}, "GahdDangitBobby": {}, "imasheep95": {}, "mahirkay1": {}, "Two-Bite-Brownies": {}, "Jukecity": {}, "DougieFresh221": {}, "Charborgg": {}, "thathealthou": {}, "Cinex": {}, "giwake": {}, "ProTeasing": {}, "BetaChad69": {}, "taeast101": {}, "Enigmaze": {}, "HotJNS": {}, "derieu": {}, "wildzx17": {}, "Schnitzel1337": {}, "FriendlyHansen": {}, "evscye": {}, "SinnerOG": {}, "Nanscope": {}, "themuseful": {}, "RedT-Shirt": {}, "Hopper4ooo": {}, "RsFan23": {}, "Neoncolorzhd": {}, "TEE-RIPPY": {}, "TempestheDragon": {}, "Korihoko": {}, "tohmmo": {}, "A_Cats_Tail": {}, "wacker9999": {}, "nagolruhtra": {}, "CakeAuNoob": {}, "PartyPatComeback": {}, "TheShaneSmith": {}, "JabbaTheHuttOSRS": {}, "AeroKy": {}, "spiritweed07": {}, "Toppi_The_Topic": {}, "Sir_Fashionscape": {}, "jdpolloc": {}, "crippledcow": {}, "FungoGolf": {}, "Peajib": {}, "Lanceloet": {}, "Kindalikecobain": {}, "Snessrek": {}, "whatsoup_": {}, "GrILLEd_Toast3r": {}, "imzeta": {}, "Ohanto": {}, "Lleytt": {}, "kahbeleth": {}, "-_-Tom-_-": {}, "AsssYouuuWish": {}, "gracetbh": {}, "thisagain42": {}, "rodentchild": {}, "sakuyasnow": {}, "buttholeitches": {}, "Pairot01": {}, "NecstNecstNecst": {}, "PurpleSweetz": {}, "rRMTmjrppnj78hFH": {}, "filliamworbes": {}, "sirfoolery": {}, "Liltwin985": {}, "otissplunk": {}, "rustbucks": {}, "CommonMisspellingBot": {}, "RikSanchezC137": {}, "lppl67": {}, "creusifer": {}, "iKingzyyy": {}, "eleakinite": {}, "Crispts": {}, "ZoobotXBL": {}, "Meeshtech": {}, "pepsiplaya": {}, "not_basic_k": {}, "Oarf_Dragon": {}, "W65_eOe": {}, "APO_OCD_80": {}, "RuinationX": {}, "dropdeadfilth": {}, "Dark4_": {}, "GlitteringLobster": {}, "h0tB0xing": {}, "not_45_def": {}, "DoSlayerReee": {}, "DWS_Gage": {}, "VanLovesCake": {}, "Zathren": {}, "Airmatic": {}, "rs_obsidian": {}, "JoeyKaws": {}, "KandiKlover": {}, "Nadeyy_": {}, "Scape2": {}, "crabtrrj": {}, "Jojaaa": {}, "Yawodo": {}, "BloodTown": {}, "thefomp": {}, "fortoreply": {}, "Woodani": {}, "AllSodiumDiet": {}, "MickMuffin27": {}, "peridea": {}, "badgehunter": {}, "Theons": {}, "ContentSaved": {}, "DearTitan": {}, "dudeidklikewhat": {}, "Bigduud": {}, "_fishies": {}, "King_Trigger": {}, "Randizzle25": {}, "MuseAZN": {}, "ReallyShortGiant": {}, "RazyRyan": {}, "Johnnyboi2g": {}, "Bimtenbo": {}, "Dualyeti": {}, "dan0314": {}, "babanis1": {}, "COCONUTPANTS76": {}, "Omg_Nefa": {}, "Zenteyy": {}, "KreaHS": {}, "ASpoonRS": {}, "Why-Do-I-Even-Try": {}, "DaKDC": {}, "1010Reddit1010": {}, "Unsunite": {}, "eriquedesigns": {}, "z0gre": {}, "OddDoktor": {}, "2MuchDip": {}, "sneakpeekbot": {}, "DMTxLSD": {}, "ElephantSacks": {}, "ch00blet": {}, "BooCMB": {}, "metalslug53": {}, "wwwwwildhero": {}, "kathleenxyz": {}, "ihkupallo": {}, "mikedip3": {}, "Gamepenuin": {}, "dan124356": {}, "TheMapleDreamer": {}, "redditor5991": {}, "that_guy_95": {}, "Valkyrie1810": {}, "mostwant_ded": {}, "odrizy": {}, "shmeh_moose": {}, "Love_Means_Nothing": {}, "Dephire": {}, "RAICH_17": {}, "Imallskillzy": {}, "FriedrichDerRote": {}, "charmingCobra": {}, "Chad661199": {}, "ArrowHen-": {}}